{
  "input_parameters": {
    "directories": {
      "kilosort_output_directory": "C:\\Users\\Python\\Desktop\\KiloSort\\LocalProcessed\\ecephystest",
      "extracted_data_directory": "C:\\Users\\Python\\Desktop\\KiloSort\\LocalProcessed\\ecephystest",
      "kilosort_output_tmp": "C:\\Users\\Python\\Desktop\\KiloSort\\LocalProcessed\\temp",
      "ecephys_directory": "C:\\Users\\Python\\Desktop\\ecephys\\ecephys_spike_sorting",
      "npx_directory": "C:\\Users\\Python\\Desktop\\KiloSort\\LocalRaw"
    },
    "catGT_helper_params": {
      "loccar_inner": 2,
      "stream_string": "-ap -ni -lf",
      "probe_string": "0",
      "loccar_outer": 8,
      "gate_string": "0",
      "car_mode": "gblcar",
      "cmdStr": "-prb_fld -out_prb_fld -apfilter=butter,12,300,10000 -lffilter=butter,12,1,500 -gfix=0.4,0.10,0.02  -SY=0,-1,6,500 -XA=0,1,3,500 -iXA=1,3,3,0  -XD=-1,1,50 -XD=-1,2,1.7 -XD=-1,3,5 -iXD=-1,3,5",
      "run_name": "A3_210122_randomforagecuerich_record1",
      "catGTPath": "C:\\Users\\Python\\Desktop\\spiketools\\CatGT-win",
      "trigger_string": "0,0"
    },
    "input_json": "C:\\Users\\Python\\Desktop\\ecephys\\jsonfiles\\A3_210122_randomforagecuerich_record10_CatGT-input.json",
    "output_json": "C:\\Users\\Python\\Desktop\\ecephys\\jsonfiles\\A3_210122_randomforagecuerich_record10_CatGT-output.json",
    "ephys_params": {
      "sample_rate": 30000.0,
      "bit_volts": 2.34375,
      "template_zero_padding": 21,
      "reference_channels": [
        191
      ],
      "ap_band_file": "C:\\Users\\Python\\Desktop\\KiloSort\\LocalRaw\\A3_210122_randomforagecuerich_record1_g0\\A3_210122_randomforagecuerich_record1_g0_imec0\\A3_210122_randomforagecuerich_record1_g0_t0.imec0.ap.bin",
      "reorder_lfp_channels": false,
      "lfp_band_file": "C:\\Users\\Python\\Desktop\\KiloSort\\LocalRaw\\A3_210122_randomforagecuerich_record1_g0\\A3_210122_randomforagecuerich_record1_g0_imec0\\A3_210122_randomforagecuerich_record1_g0_t0.imec0.lf.bin",
      "num_channels": 385,
      "vertical_site_spacing": 1e-05,
      "lfp_sample_rate": 2500.0,
      "probe_type": "NP1",
      "cluster_group_file_name": "cluster_group.tsv"
    },
    "log_level": "ERROR"
  },
  "execution_time": 656.7209725379944
}